scoptrial/__init__.py
scoptrial/_nbdev.py
scoptrial/core.py
scoptrial/scop-linux
scoptrial/scop-mac
scoptrial/scop-win.exe
scoptrial/scop.py
scoptrial-0.1.1.dist-info/LICENSE
scoptrial-0.1.1.dist-info/WHEEL
scoptrial-0.1.1.dist-info/METADATA
scoptrial-0.1.1.dist-info/RECORD
