Metadata-Version: 2.1
Name: scoptrial
Version: 0.1.1
Summary: 
Author: mikiokubo
Author-email: kubo@kaiyodai.ac.jp
Requires-Python: >=3.8,<4.0
Classifier: Programming Language :: Python :: 3
Classifier: Programming Language :: Python :: 3.8
Classifier: Programming Language :: Python :: 3.9
Requires-Dist: jupyterlab (>=2.2.9,<3.0.0)
Requires-Dist: matplotlib (>=3.3.3,<4.0.0)
Requires-Dist: nbdev (>=1.1.5,<2.0.0)
Requires-Dist: pandas (>=1.1.4,<2.0.0)
Requires-Dist: plotly (>=4.13.0,<5.0.0)
